setup.py
wechatSpider/__init__.py
wechatSpider.egg-info/PKG-INFO
wechatSpider.egg-info/SOURCES.txt
wechatSpider.egg-info/dependency_links.txt
wechatSpider.egg-info/requires.txt
wechatSpider.egg-info/top_level.txt