Metadata-Version: 1.0
Name: wechatSpider
Version: 0.2
Summary: WeChat subscription search by lshxiao
Home-page: http://py.pxuexiao.com/wechat_spider/index.html
Author: lshxiao
Author-email: lshxiao@163.com
License: http://web.pxuexiao.com
Platform: python 2.7
